swanportallocator/__init__.py
swanportallocator/_version.py
swanportallocator/portallocator.py
swanportallocator-2.0.0.data/data/etc/jupyter/jupyter_server_config.d/swanportallocator.json
swanportallocator-2.0.0.dist-info/METADATA
swanportallocator-2.0.0.dist-info/WHEEL
swanportallocator-2.0.0.dist-info/top_level.txt
swanportallocator-2.0.0.dist-info/RECORD
